Metadata-Version: 2.1
Name: interestinghumanfacts1
Version: 0.1
Summary: Computes interesting facts for an average human being based in the user inputs
Home-page: UNKNOWN
Author: Santiago RUIZ
Author-email: santiagoruiamoreno@outlook.fr
License: UNKNOWN
Platform: UNKNOWN
